colonel/__init__.py
colonel/base_rich_sentence_element.py
colonel/base_sentence_element.py
colonel/emptynode.py
colonel/multiword.py
colonel/py.typed
colonel/sentence.py
colonel/upostag.py
colonel/word.py
colonel/conllu/__init__.py
colonel/conllu/lexer.py
colonel/conllu/parser.py
colonel-2.0.1.dist-info/LICENSE
colonel-2.0.1.dist-info/METADATA
colonel-2.0.1.dist-info/WHEEL
colonel-2.0.1.dist-info/top_level.txt
colonel-2.0.1.dist-info/RECORD
