Metadata-Version: 2.1
Name: colonel
Version: 2.0.1
Summary: A Python 3 library for handling CoNLL data formats
Home-page: https://github.com/nlpodyssey/colonel
Author: The NLP Odyssey Authors
Maintainer: Marco Nicola
Maintainer-email: marconicola@disroot.org
License: Apache-2.0
Keywords: conll conllu dependency parsing
Platform: UNKNOWN
Classifier: Development Status :: 5 - Production/Stable
Classifier: Intended Audience :: Developers
Classifier: Intended Audience :: Science/Research
Classifier: License :: OSI Approved :: Apache Software License
Classifier: Programming Language :: Python :: 3
Classifier: Programming Language :: Python :: 3 :: Only
Classifier: Programming Language :: Python :: 3.7
Classifier: Topic :: Scientific/Engineering
Classifier: Topic :: Scientific/Engineering :: Artificial Intelligence
Classifier: Topic :: Scientific/Engineering :: Human Machine Interfaces
Classifier: Topic :: Scientific/Engineering :: Information Analysis
Classifier: Topic :: Software Development :: Libraries
Classifier: Topic :: Text Processing :: Linguistic
Classifier: Topic :: Utilities
Requires-Python: >=3.7, <4
Requires-Dist: ply (<4,>=3)
